celtis/Cli.py
celtis/Config.py
celtis/Logger.py
celtis/Rule.py
celtis/Scanner.py
celtis/Target.py
celtis/__init__.py
celtis/__main__.py
celtis-0.1.0.dist-info/LICENSE.md
celtis-0.1.0.dist-info/METADATA
celtis-0.1.0.dist-info/WHEEL
celtis-0.1.0.dist-info/entry_points.txt
celtis-0.1.0.dist-info/top_level.txt
celtis-0.1.0.dist-info/RECORD
